{
  "metodo": "smote",
  "proporcion_config": {
    "11": 25000,
    "3": 50000,
    "7": 50000,
    "6": 25000,
    "5": 25000
  },
  "resumen": {
    "muestras_antes": 44240,
    "muestras_despues": 194444,
    "incremento_total": 150204
  },
  "distribucion_original": {
    "11.0": 4128,
    "3.0": 7205,
    "7.0": 5557,
    "6.0": 4057,
    "5.0": 3849,
    "0.0": 15492,
    "4.0": 1749,
    "2.0": 969,
    "10.0": 1203,
    "12.0": 11,
    "14.0": 5,
    "1.0": 15
  },
  "distribucion_final": {
    "11.0": 25000,
    "3.0": 50000,
    "7.0": 50000,
    "6.0": 25000,
    "5.0": 25000,
    "0.0": 15492,
    "4.0": 1749,
    "2.0": 969,
    "10.0": 1203,
    "12.0": 11,
    "14.0": 5,
    "1.0": 15
  },
  "analisis_por_clase": {
    "0.0": {
      "estado": "Intacto",
      "originales": 15492,
      "finales": 15492,
      "sinteticas_puras_detectadas": 0,
      "multiplicador": 1.0
    },
    "1.0": {
      "estado": "Intacto",
      "originales": 15,
      "finales": 15,
      "sinteticas_puras_detectadas": 0,
      "multiplicador": 1.0
    },
    "2.0": {
      "estado": "Intacto",
      "originales": 969,
      "finales": 969,
      "sinteticas_puras_detectadas": 0,
      "multiplicador": 1.0
    },
    "3.0": {
      "estado": "Oversampled",
      "originales": 7205,
      "finales": 50000,
      "sinteticas_puras_detectadas": 42795,
      "multiplicador": 6.94,
      "metricas_vecindario": {
        "distancia_media_interna_original": 0.082038,
        "distancia_media_sinteticos_a_originales": 0.03355,
        "porcentaje_duplicados_exactos": 1.63,
        "riesgo_artefactos": "Bajo (Consistente)"
      }
    },
    "4.0": {
      "estado": "Intacto",
      "originales": 1749,
      "finales": 1749,
      "sinteticas_puras_detectadas": 0,
      "multiplicador": 1.0
    },
    "5.0": {
      "estado": "Oversampled",
      "originales": 3849,
      "finales": 25000,
      "sinteticas_puras_detectadas": 21151,
      "multiplicador": 6.5,
      "metricas_vecindario": {
        "distancia_media_interna_original": 0.019706,
        "distancia_media_sinteticos_a_originales": 0.011058,
        "porcentaje_duplicados_exactos": 6.35,
        "riesgo_artefactos": "Alto (Alerta de Duplicidad: 6.4%)"
      }
    },
    "6.0": {
      "estado": "Oversampled",
      "originales": 4057,
      "finales": 25000,
      "sinteticas_puras_detectadas": 20943,
      "multiplicador": 6.16,
      "metricas_vecindario": {
        "distancia_media_interna_original": 0.023904,
        "distancia_media_sinteticos_a_originales": 0.010829,
        "porcentaje_duplicados_exactos": 3.7,
        "riesgo_artefactos": "Bajo (Consistente)"
      }
    },
    "7.0": {
      "estado": "Oversampled",
      "originales": 5557,
      "finales": 50000,
      "sinteticas_puras_detectadas": 44443,
      "multiplicador": 9.0,
      "metricas_vecindario": {
        "distancia_media_interna_original": 0.00309,
        "distancia_media_sinteticos_a_originales": 0.002479,
        "porcentaje_duplicados_exactos": 4.73,
        "riesgo_artefactos": "Bajo (Consistente)"
      }
    },
    "10.0": {
      "estado": "Intacto",
      "originales": 1203,
      "finales": 1203,
      "sinteticas_puras_detectadas": 0,
      "multiplicador": 1.0
    },
    "11.0": {
      "estado": "Oversampled",
      "originales": 4128,
      "finales": 25000,
      "sinteticas_puras_detectadas": 20872,
      "multiplicador": 6.06,
      "metricas_vecindario": {
        "distancia_media_interna_original": 0.012061,
        "distancia_media_sinteticos_a_originales": 0.005747,
        "porcentaje_duplicados_exactos": 4.11,
        "riesgo_artefactos": "Bajo (Consistente)"
      }
    },
    "12.0": {
      "estado": "Intacto",
      "originales": 11,
      "finales": 11,
      "sinteticas_puras_detectadas": 0,
      "multiplicador": 1.0
    },
    "14.0": {
      "estado": "Intacto",
      "originales": 5,
      "finales": 5,
      "sinteticas_puras_detectadas": 0,
      "multiplicador": 1.0
    }
  }
}